ppte/TE_real.py
ppte/__init__.py
ppte/__main__.py
ppte/build_pool.py
ppte/compare_vcf.py
ppte/reads.py
ppte/simulate.py
ppte-0.7.0.dist-info/licenses/LICENSE
ppte-0.7.0.dist-info/METADATA
ppte-0.7.0.dist-info/WHEEL
ppte-0.7.0.dist-info/entry_points.txt
ppte-0.7.0.dist-info/top_level.txt
ppte-0.7.0.dist-info/RECORD
