Metadata-Version: 2.4
Name: PPTE
Version: 0.7.0
Summary: PPTEs: A Pangenome Polymorphic Transposable Elements simulation toolkit
Home-page: https://github.com/yourusername/ppte
Author: JIAN MIAO
Author-email: miaojian6363@gmail.com
Classifier: Programming Language :: Python :: 3
Classifier: License :: OSI Approved :: MIT License
Classifier: Operating System :: OS Independent
Requires-Python: >=3.8
License-File: LICENSE
Requires-Dist: numpy
Requires-Dist: biopython
Requires-Dist: pysam
Dynamic: author
Dynamic: author-email
Dynamic: classifier
Dynamic: description
Dynamic: description-content-type
Dynamic: home-page
Dynamic: license-file
Dynamic: requires-dist
Dynamic: requires-python
Dynamic: summary
